{
    "open_counters": 7,
    "closed_counters": 5,
    "total_counters": 12,
    "customers_in_queue": 20,
    "avg_wait_time": "10+ minutes",
    "queue_efficiency": "inefficient",
    "overcrowded_counters": true,
    "recommendations": [
        "Optimize Staffing",
        "Implement Dynamic Queue Management",
        "Enhance Self-Checkout Options",
        "Monitor and Adjust"
    ],
    "vision_raw_response": "**Step 1: Count the approximate number of checkout counters that appear to be open (staffed/operational)**\n\nIn the image, there are 7 checkout counters that appear to be open and staffed. These counters have a cashier or attendant present, indicating that they are operational.\n\n**Step 2: Count the approximate number of checkout counters that appear to be closed (unstaffed/non-operational)**\n\nThere are 5 checkout counters that appear to be closed and unstaffed. These counters do not have a cashier or attendant present, suggesting that they are not operational at the moment.\n\n**Step 3: Estimate the total number of customers waiting in checkout lines**\n\nUpon reviewing the image, it is estimated that there are approximately 20 customers waiting in the various checkout lines. This number may vary slightly depending on the exact count, but 20 provides a reasonable estimate.\n\n**Step 4: Assess the efficiency of the current queue management setup**\n\nThe current queue management setup appears to have some inefficiencies. With only 7 operational checkout counters and a relatively high number of customers waiting (approximately 20), there is likely a significant wait time for customers. Additionally, the presence of 5 unstaffed counters suggests underutilization of available resources, which could contribute to longer wait times during peak periods.\n\n**Step 5: Suggest business recommendations to improve customer flow and reduce wait times**\n\nTo optimize customer flow and reduce wait times, the following recommendations are proposed:\n\n* **Optimize Staffing**: Ensure that all available checkout counters are staffed during peak periods to maximize capacity and minimize wait times.\n* **Implement Dynamic Queue Management**: Consider implementing a dynamic queue management system that directs customers to the shortest line or opens additional lanes during busy times to distribute the workload more evenly.\n* **Enhance Self-Checkout Options**: Consider increasing the number of self-checkout lanes or improving their efficiency to provide customers with an alternative to traditional checkout lines.\n* **Monitor and Adjust**: Continuously monitor customer flow and wait times to identify areas for improvement and make data-driven adjustments to staffing and queue management strategies.\n\nBy implementing these recommendations, the retail business can enhance the overall shopping experience, reduce wait times, and improve operational efficiency.",
    "text_raw_response": "```json\n{\n  \"opencounters\": 7,\n  \"closedcounters\": 5,\n  \"totalcounters\": 12,\n  \"customersinqueue\": 20,\n  \"waittime\": \"10+ minutes\",\n  \"queueefficiency\": \"inefficient\",\n  \"overcrowded\": true,\n  \"recommendations\": [\n    \"Optimize Staffing\",\n    \"Implement Dynamic Queue Management\",\n    \"Enhance Self-Checkout Options\",\n    \"Monitor and Adjust\"\n  ]\n}\n```",
    "raw_response": "**Step 1: Count the approximate number of checkout counters that appear to be open (staffed/operational)**\n\nIn the image, there are 7 checkout counters that appear to be open and staffed. These counters have a cashier or attendant present, indicating that they are operational.\n\n**Step 2: Count the approximate number of checkout counters that appear to be closed (unstaffed/non-operational)**\n\nThere are 5 checkout counters that appear to be closed and unstaffed. These counters do not have a cashier or attendant present, suggesting that they are not operational at the moment.\n\n**Step 3: Estimate the total number of customers waiting in checkout lines**\n\nUpon reviewing the image, it is estimated that there are approximately 20 customers waiting in the various checkout lines. This number may vary slightly depending on the exact count, but 20 provides a reasonable estimate.\n\n**Step 4: Assess the efficiency of the current queue management setup**\n\nThe current queue management setup appears to have some inefficiencies. With only 7 operational checkout counters and a relatively high number of customers waiting (approximately 20), there is likely a significant wait time for customers. Additionally, the presence of 5 unstaffed counters suggests underutilization of available resources, which could contribute to longer wait times during peak periods.\n\n**Step 5: Suggest business recommendations to improve customer flow and reduce wait times**\n\nTo optimize customer flow and reduce wait times, the following recommendations are proposed:\n\n* **Optimize Staffing**: Ensure that all available checkout counters are staffed during peak periods to maximize capacity and minimize wait times.\n* **Implement Dynamic Queue Management**: Consider implementing a dynamic queue management system that directs customers to the shortest line or opens additional lanes during busy times to distribute the workload more evenly.\n* **Enhance Self-Checkout Options**: Consider increasing the number of self-checkout lanes or improving their efficiency to provide customers with an alternative to traditional checkout lines.\n* **Monitor and Adjust**: Continuously monitor customer flow and wait times to identify areas for improvement and make data-driven adjustments to staffing and queue management strategies.\n\nBy implementing these recommendations, the retail business can enhance the overall shopping experience, reduce wait times, and improve operational efficiency.",
    "is_mock": false
}